charzsh/__init__.py
charzsh/backup.py
charzsh/delete_backedup.py
charzsh/eta.py
charzsh/fix_io_errors.py
charzsh/k8s_cfg.py
charzsh/utils.py
charzsh-0.0.6.dist-info/METADATA
charzsh-0.0.6.dist-info/WHEEL
charzsh-0.0.6.dist-info/entry_points.txt
charzsh-0.0.6.dist-info/top_level.txt
charzsh-0.0.6.dist-info/RECORD
