Metadata-Version: 2.1
Name: charzsh
Version: 0.0.6
Summary: Charzsh
Home-page: https://gitlab.com/amirmd76/charzsh.git
Author: AmirMohammad Dehghan
Author-email: amirmd76@gmail.com
License: MIT
Platform: UNKNOWN
Requires-Dist: python-dateutil
